cbler/__init__.py
cbler/code_cmd.py
cbler/git_cmd.py
cbler/git_commands.py
cbler/main.py
cbler/report.py
cbler/utils.py
cbler-1.2.0.dist-info/WHEEL
cbler-1.2.0.dist-info/entry_points.txt
cbler-1.2.0.dist-info/METADATA
cbler-1.2.0.dist-info/RECORD
