Metadata-Version: 2.3
Name: cbler
Version: 1.2.0
Summary: Extensible code concatenator and clipboard tool
Requires-Dist: pydantic>=2.11.7
Requires-Dist: pyperclip>=1.9.0
Requires-Dist: rich>=14.0.0
Requires-Dist: textual>=5.0.1
Requires-Dist: typer[all]>=0.16.0
Requires-Python: >=3.12
